{
  "Width": 38.25,
  "Height": 49.5,
  "HLines": [],
  "VLines": [],
  "Fills": [],
  "Texts": [
    {
      "x": 3.072,
      "y": 11.896,
      "w": 37.981,
      "clr": 0,
      "sw": 0.36196875,
      "A": "left",
      "R": [
        {
          "T": "Placement",
          "S": -1,
          "TS": [
            0,
            11.04,
            0,
            0
          ]
        }
      ]
    },
    {
      "x": 5.729,
      "y": 11.896,
      "w": 29.04,
      "clr": 0,
      "sw": 0.36196875,
      "A": "left",
      "R": [
        {
          "T": "Entry ID",
          "S": -1,
          "TS": [
            0,
            11.04,
            0,
            0
          ]
        }
      ]
    },
    {
      "x": 10.086,
      "y": 11.896,
      "w": 46.471,
      "clr": 0,
      "sw": 0.36196875,
      "A": "left",
      "R": [
        {
          "T": "Studio Name",
          "S": -1,
          "TS": [
            0,
            11.04,
            0,
            0
          ]
        }
      ]
    },
    {
      "x": 17.993,
      "y": 11.896,
      "w": 45.129,
      "clr": 0,
      "sw": 0.36196875,
      "A": "left",
      "R": [
        {
          "T": "Routine Title",
          "S": -1,
          "TS": [
            0,
            11.04,
            0,
            0
          ]
        }
      ]
    },
    {
      "x": 25.209,
      "y": 11.896,
      "w": 47.806,
      "clr": 0,
      "sw": 0.36196875,
      "A": "left",
      "R": [
        {
          "T": "Soloist Name",
          "S": -1,
          "TS": [
            0,
            11.04,
            0,
            0
          ]
        }
      ]
    },
    {
      "x": 3.087,
      "y": 12.804,
      "w": 37.965,
      "clr": 0,
      "sw": 0.36196875,
      "A": "left",
      "R": [
        {
          "T": "DIAMOND",
          "S": -1,
          "TS": [
            0,
            11.04,
            0,
            0
          ]
        }
      ]
    },
    {
      "x": 6.494,
      "y": 12.856,
      "w": 4.47,
      "clr": 0,
      "sw": 0.36196875,
      "A": "left",
      "R": [
        {
          "T": "6",
          "S": -1,
          "TS": [
            0,
            11.04,
            0,
            0
          ]
        }
      ]
    },
    {
      "x": 8.714,
      "y": 12.856,
      "w": 90.699,
      "clr": 0,
      "sw": 0.36196875,
      "A": "left",
      "R": [
        {
          "T": "Rise Up Dance Company",
          "S": -1,
          "TS": [
            0,
            11.04,
            0,
            0
          ]
        }
      ]
    },
    {
      "x": 16.471,
      "y": 12.856,
      "w": 93.57,
      "clr": 0,
      "sw": 0.36196875,
      "A": "left",
      "R": [
        {
          "T": "DANCE LIKE YO' DADDY",
          "S": -1,
          "TS": [
            0,
            11.04,
            0,
            0
          ]
        }
      ]
    },
    {
      "x": 24.474,
      "y": 12.856,
      "w": 71.033,
      "clr": 0,
      "sw": 0.36196875,
      "A": "left",
      "R": [
        {
          "T": "WESSLYN SMITH  ",
          "S": -1,
          "TS": [
            0,
            11.04,
            0,
            0
          ]
        }
      ]
    },
    {
      "x": 3.569,
      "y": 13.711,
      "w": 22.335,
      "clr": 0,
      "sw": 0.36196875,
      "A": "left",
      "R": [
        {
          "T": "RUBY",
          "S": -1,
          "TS": [
            0,
            11.04,
            0,
            0
          ]
        }
      ]
    },
    {
      "x": 6.494,
      "y": 13.764,
      "w": 4.47,
      "clr": 0,
      "sw": 0.36196875,
      "A": "left",
      "R": [
        {
          "T": "5",
          "S": -1,
          "TS": [
            0,
            11.04,
            0,
            0
          ]
        }
      ]
    },
    {
      "x": 9.209,
      "y": 13.764,
      "w": 75.045,
      "clr": 0,
      "sw": 0.36196875,
      "A": "left",
      "R": [
        {
          "T": "Music Moves Me NM",
          "S": -1,
          "TS": [
            0,
            11.04,
            0,
            0
          ]
        }
      ]
    },
    {
      "x": 17.513,
      "y": 13.764,
      "w": 60.3,
      "clr": 0,
      "sw": 0.36196875,
      "A": "left",
      "R": [
        {
          "T": "FIX MY CROWN",
          "S": -1,
          "TS": [
            0,
            11.04,
            0,
            0
          ]
        }
      ]
    },
    {
      "x": 24.474,
      "y": 13.764,
      "w": 71.049,
      "clr": 0,
      "sw": 0.36196875,
      "A": "left",
      "R": [
        {
          "T": "EVELYNN SPAKE  ",
          "S": -1,
          "TS": [
            0,
            11.04,
            0,
            0
          ]
        }
      ]
    },
    {
      "x": 3.057,
      "y": 14.621,
      "w": 38.865,
      "clr": 0,
      "sw": 0.36196875,
      "A": "left",
      "R": [
        {
          "T": "EMERALD",
          "S": -1,
          "TS": [
            0,
            11.04,
            0,
            0
          ]
        }
      ]
    },
    {
      "x": 6.494,
      "y": 14.673,
      "w": 4.47,
      "clr": 0,
      "sw": 0.36196875,
      "A": "left",
      "R": [
        {
          "T": "3",
          "S": -1,
          "TS": [
            0,
            11.04,
            0,
            0
          ]
        }
      ]
    },
    {
      "x": 8.384,
      "y": 14.673,
      "w": 100.99,
      "clr": 0,
      "sw": 0.36196875,
      "A": "left",
      "R": [
        {
          "T": "Dancing Stars Dance Studio",
          "S": -1,
          "TS": [
            0,
            11.04,
            0,
            0
          ]
        }
      ]
    },
    {
      "x": 16.748,
      "y": 14.673,
      "w": 84.886,
      "clr": 0,
      "sw": 0.36196875,
      "A": "left",
      "R": [
        {
          "T": "I REALLY DONT CARE",
          "S": -1,
          "TS": [
            0,
            11.04,
            0,
            0
          ]
        }
      ]
    },
    {
      "x": 24.272,
      "y": 14.673,
      "w": 77.747,
      "clr": 0,
      "sw": 0.36196875,
      "A": "left",
      "R": [
        {
          "T": "APOLLONIA DIMAS  ",
          "S": -1,
          "TS": [
            0,
            11.04,
            0,
            0
          ]
        }
      ]
    },
    {
      "x": 2.99,
      "y": 15.527999999999999,
      "w": 40.658,
      "clr": 0,
      "sw": 0.36196875,
      "A": "left",
      "R": [
        {
          "T": "SAPPHIRE",
          "S": -1,
          "TS": [
            0,
            11.04,
            0,
            0
          ]
        }
      ]
    },
    {
      "x": 6.494,
      "y": 15.581,
      "w": 4.47,
      "clr": 0,
      "sw": 0.36196875,
      "A": "left",
      "R": [
        {
          "T": "7",
          "S": -1,
          "TS": [
            0,
            11.04,
            0,
            0
          ]
        }
      ]
    },
    {
      "x": 9.209,
      "y": 15.581,
      "w": 75.045,
      "clr": 0,
      "sw": 0.36196875,
      "A": "left",
      "R": [
        {
          "T": "Music Moves Me NM",
          "S": -1,
          "TS": [
            0,
            11.04,
            0,
            0
          ]
        }
      ]
    },
    {
      "x": 18.031,
      "y": 15.581,
      "w": 43.786,
      "clr": 0,
      "sw": 0.36196875,
      "A": "left",
      "R": [
        {
          "T": "NUEVAYOL",
          "S": -1,
          "TS": [
            0,
            11.04,
            0,
            0
          ]
        }
      ]
    },
    {
      "x": 24.594,
      "y": 15.581,
      "w": 67.464,
      "clr": 0,
      "sw": 0.36196875,
      "A": "left",
      "R": [
        {
          "T": "ABRIELLE CRUZ  ",
          "S": -1,
          "TS": [
            0,
            11.04,
            0,
            0
          ]
        }
      ]
    },
    {
      "x": 3.072,
      "y": 17.523,
      "w": 37.981,
      "clr": 0,
      "sw": 0.36196875,
      "A": "left",
      "R": [
        {
          "T": "Placement",
          "S": -1,
          "TS": [
            0,
            11.04,
            0,
            0
          ]
        }
      ]
    },
    {
      "x": 5.729,
      "y": 17.523,
      "w": 29.04,
      "clr": 0,
      "sw": 0.36196875,
      "A": "left",
      "R": [
        {
          "T": "Entry ID",
          "S": -1,
          "TS": [
            0,
            11.04,
            0,
            0
          ]
        }
      ]
    },
    {
      "x": 10.086,
      "y": 17.523,
      "w": 46.471,
      "clr": 0,
      "sw": 0.36196875,
      "A": "left",
      "R": [
        {
          "T": "Studio Name",
          "S": -1,
          "TS": [
            0,
            11.04,
            0,
            0
          ]
        }
      ]
    },
    {
      "x": 17.993,
      "y": 17.523,
      "w": 45.129,
      "clr": 0,
      "sw": 0.36196875,
      "A": "left",
      "R": [
        {
          "T": "Routine Title",
          "S": -1,
          "TS": [
            0,
            11.04,
            0,
            0
          ]
        }
      ]
    },
    {
      "x": 3.087,
      "y": 18.431,
      "w": 37.965,
      "clr": 0,
      "sw": 0.36196875,
      "A": "left",
      "R": [
        {
          "T": "DIAMOND",
          "S": -1,
          "TS": [
            0,
            11.04,
            0,
            0
          ]
        }
      ]
    },
    {
      "x": 6.494,
      "y": 18.483,
      "w": 4.47,
      "clr": 0,
      "sw": 0.36196875,
      "A": "left",
      "R": [
        {
          "T": "8",
          "S": -1,
          "TS": [
            0,
            11.04,
            0,
            0
          ]
        }
      ]
    },
    {
      "x": 8.384,
      "y": 18.483,
      "w": 100.99,
      "clr": 0,
      "sw": 0.36196875,
      "A": "left",
      "R": [
        {
          "T": "Dancing Stars Dance Studio",
          "S": -1,
          "TS": [
            0,
            11.04,
            0,
            0
          ]
        }
      ]
    },
    {
      "x": 18.406,
      "y": 18.483,
      "w": 31.718,
      "clr": 0,
      "sw": 0.36196875,
      "A": "left",
      "R": [
        {
          "T": "PUSH IT",
          "S": -1,
          "TS": [
            0,
            11.04,
            0,
            0
          ]
        }
      ]
    },
    {
      "x": 3.072,
      "y": 20.426,
      "w": 37.981,
      "clr": 0,
      "sw": 0.36196875,
      "A": "left",
      "R": [
        {
          "T": "Placement",
          "S": -1,
          "TS": [
            0,
            11.04,
            0,
            0
          ]
        }
      ]
    },
    {
      "x": 5.729,
      "y": 20.426,
      "w": 29.04,
      "clr": 0,
      "sw": 0.36196875,
      "A": "left",
      "R": [
        {
          "T": "Entry ID",
          "S": -1,
          "TS": [
            0,
            11.04,
            0,
            0
          ]
        }
      ]
    },
    {
      "x": 10.086,
      "y": 20.426,
      "w": 46.471,
      "clr": 0,
      "sw": 0.36196875,
      "A": "left",
      "R": [
        {
          "T": "Studio Name",
          "S": -1,
          "TS": [
            0,
            11.04,
            0,
            0
          ]
        }
      ]
    },
    {
      "x": 17.993,
      "y": 20.426,
      "w": 45.129,
      "clr": 0,
      "sw": 0.36196875,
      "A": "left",
      "R": [
        {
          "T": "Routine Title",
          "S": -1,
          "TS": [
            0,
            11.04,
            0,
            0
          ]
        }
      ]
    },
    {
      "x": 3.087,
      "y": 21.333,
      "w": 37.965,
      "clr": 0,
      "sw": 0.36196875,
      "A": "left",
      "R": [
        {
          "T": "DIAMOND",
          "S": -1,
          "TS": [
            0,
            11.04,
            0,
            0
          ]
        }
      ]
    },
    {
      "x": 6.216,
      "y": 21.386,
      "w": 13.32,
      "clr": 0,
      "sw": 0.36196875,
      "A": "left",
      "R": [
        {
          "T": "112",
          "S": -1,
          "TS": [
            0,
            11.04,
            0,
            0
          ]
        }
      ]
    },
    {
      "x": 7.671,
      "y": 21.386,
      "w": 123.776,
      "clr": 0,
      "sw": 0.36196875,
      "A": "left",
      "R": [
        {
          "T": "Aspire Dance Company of El Paso",
          "S": -1,
          "TS": [
            0,
            11.04,
            0,
            0
          ]
        }
      ]
    },
    {
      "x": 16.846,
      "y": 21.386,
      "w": 81.317,
      "clr": 0,
      "sw": 0.36196875,
      "A": "left",
      "R": [
        {
          "T": "FEEL LIKE A WOMAN",
          "S": -1,
          "TS": [
            0,
            11.04,
            0,
            0
          ]
        }
      ]
    },
    {
      "x": 3.569,
      "y": 22.241,
      "w": 22.335,
      "clr": 0,
      "sw": 0.36196875,
      "A": "left",
      "R": [
        {
          "T": "RUBY",
          "S": -1,
          "TS": [
            0,
            11.04,
            0,
            0
          ]
        }
      ]
    },
    {
      "x": 6.216,
      "y": 22.293,
      "w": 13.32,
      "clr": 0,
      "sw": 0.36196875,
      "A": "left",
      "R": [
        {
          "T": "111",
          "S": -1,
          "TS": [
            0,
            11.04,
            0,
            0
          ]
        }
      ]
    },
    {
      "x": 8.384,
      "y": 22.293,
      "w": 100.99,
      "clr": 0,
      "sw": 0.36196875,
      "A": "left",
      "R": [
        {
          "T": "Dancing Stars Dance Studio",
          "S": -1,
          "TS": [
            0,
            11.04,
            0,
            0
          ]
        }
      ]
    },
    {
      "x": 17.851,
      "y": 22.293,
      "w": 49.591,
      "clr": 0,
      "sw": 0.36196875,
      "A": "left",
      "R": [
        {
          "T": "MEAN GIRLS",
          "S": -1,
          "TS": [
            0,
            11.04,
            0,
            0
          ]
        }
      ]
    },
    {
      "x": 3.072,
      "y": 24.236,
      "w": 37.981,
      "clr": 0,
      "sw": 0.36196875,
      "A": "left",
      "R": [
        {
          "T": "Placement",
          "S": -1,
          "TS": [
            0,
            11.04,
            0,
            0
          ]
        }
      ]
    },
    {
      "x": 5.729,
      "y": 24.236,
      "w": 29.04,
      "clr": 0,
      "sw": 0.36196875,
      "A": "left",
      "R": [
        {
          "T": "Entry ID",
          "S": -1,
          "TS": [
            0,
            11.04,
            0,
            0
          ]
        }
      ]
    },
    {
      "x": 10.086,
      "y": 24.236,
      "w": 46.471,
      "clr": 0,
      "sw": 0.36196875,
      "A": "left",
      "R": [
        {
          "T": "Studio Name",
          "S": -1,
          "TS": [
            0,
            11.04,
            0,
            0
          ]
        }
      ]
    },
    {
      "x": 17.993,
      "y": 24.236,
      "w": 45.129,
      "clr": 0,
      "sw": 0.36196875,
      "A": "left",
      "R": [
        {
          "T": "Routine Title",
          "S": -1,
          "TS": [
            0,
            11.04,
            0,
            0
          ]
        }
      ]
    },
    {
      "x": 25.209,
      "y": 24.236,
      "w": 47.806,
      "clr": 0,
      "sw": 0.36196875,
      "A": "left",
      "R": [
        {
          "T": "Soloist Name",
          "S": -1,
          "TS": [
            0,
            11.04,
            0,
            0
          ]
        }
      ]
    },
    {
      "x": 3.087,
      "y": 25.144,
      "w": 37.965,
      "clr": 0,
      "sw": 0.36196875,
      "A": "left",
      "R": [
        {
          "T": "DIAMOND",
          "S": -1,
          "TS": [
            0,
            11.04,
            0,
            0
          ]
        }
      ]
    },
    {
      "x": 6.359,
      "y": 25.197,
      "w": 8.88,
      "clr": 0,
      "sw": 0.36196875,
      "A": "left",
      "R": [
        {
          "T": "14",
          "S": -1,
          "TS": [
            0,
            11.04,
            0,
            0
          ]
        }
      ]
    },
    {
      "x": 8.256,
      "y": 25.197,
      "w": 105.018,
      "clr": 0,
      "sw": 0.36196875,
      "A": "left",
      "R": [
        {
          "T": "Fishback Studio of the Dance",
          "S": -1,
          "TS": [
            0,
            11.04,
            0,
            0
          ]
        }
      ]
    },
    {
      "x": 18.496,
      "y": 25.197,
      "w": 29.032,
      "clr": 0,
      "sw": 0.36196875,
      "A": "left",
      "R": [
        {
          "T": "DREAM",
          "S": -1,
          "TS": [
            0,
            11.04,
            0,
            0
          ]
        }
      ]
    },
    {
      "x": 24.692,
      "y": 25.197,
      "w": 64.336,
      "clr": 0,
      "sw": 0.36196875,
      "A": "left",
      "R": [
        {
          "T": "MILA ROBERTS  ",
          "S": -1,
          "TS": [
            0,
            11.04,
            0,
            0
          ]
        }
      ]
    },
    {
      "x": 3.569,
      "y": 26.052,
      "w": 22.335,
      "clr": 0,
      "sw": 0.36196875,
      "A": "left",
      "R": [
        {
          "T": "RUBY",
          "S": -1,
          "TS": [
            0,
            11.04,
            0,
            0
          ]
        }
      ]
    },
    {
      "x": 6.359,
      "y": 26.104,
      "w": 8.88,
      "clr": 0,
      "sw": 0.36196875,
      "A": "left",
      "R": [
        {
          "T": "12",
          "S": -1,
          "TS": [
            0,
            11.04,
            0,
            0
          ]
        }
      ]
    },
    {
      "x": 9.209,
      "y": 26.104,
      "w": 75.045,
      "clr": 0,
      "sw": 0.36196875,
      "A": "left",
      "R": [
        {
          "T": "Music Moves Me NM",
          "S": -1,
          "TS": [
            0,
            11.04,
            0,
            0
          ]
        }
      ]
    },
    {
      "x": 18.151,
      "y": 26.104,
      "w": 39.758,
      "clr": 0,
      "sw": 0.36196875,
      "A": "left",
      "R": [
        {
          "T": "FLOWERS",
          "S": -1,
          "TS": [
            0,
            11.04,
            0,
            0
          ]
        }
      ]
    },
    {
      "x": 24.144,
      "y": 26.104,
      "w": 81.759,
      "clr": 0,
      "sw": 0.36196875,
      "A": "left",
      "R": [
        {
          "T": "KENNADEE GARCIA  ",
          "S": -1,
          "TS": [
            0,
            11.04,
            0,
            0
          ]
        }
      ]
    },
    {
      "x": 3.057,
      "y": 26.959,
      "w": 38.865,
      "clr": 0,
      "sw": 0.36196875,
      "A": "left",
      "R": [
        {
          "T": "EMERALD",
          "S": -1,
          "TS": [
            0,
            11.04,
            0,
            0
          ]
        }
      ]
    },
    {
      "x": 6.359,
      "y": 27.012,
      "w": 8.88,
      "clr": 0,
      "sw": 0.36196875,
      "A": "left",
      "R": [
        {
          "T": "15",
          "S": -1,
          "TS": [
            0,
            11.04,
            0,
            0
          ]
        }
      ]
    },
    {
      "x": 8.879,
      "y": 27.012,
      "w": 85.337,
      "clr": 0,
      "sw": 0.36196875,
      "A": "left",
      "R": [
        {
          "T": "Michaelas Dance Magic",
          "S": -1,
          "TS": [
            0,
            11.04,
            0,
            0
          ]
        }
      ]
    },
    {
      "x": 16.178,
      "y": 27.012,
      "w": 103.193,
      "clr": 0,
      "sw": 0.36196875,
      "A": "left",
      "R": [
        {
          "T": "HOLDING ON FOR A HERO",
          "S": -1,
          "TS": [
            0,
            11.04,
            0,
            0
          ]
        }
      ]
    },
    {
      "x": 24.692,
      "y": 27.012,
      "w": 64.336,
      "clr": 0,
      "sw": 0.36196875,
      "A": "left",
      "R": [
        {
          "T": "GRACE DANIEL  ",
          "S": -1,
          "TS": [
            0,
            11.04,
            0,
            0
          ]
        }
      ]
    },
    {
      "x": 2.99,
      "y": 27.867,
      "w": 40.658,
      "clr": 0,
      "sw": 0.36196875,
      "A": "left",
      "R": [
        {
          "T": "SAPPHIRE",
          "S": -1,
          "TS": [
            0,
            11.04,
            0,
            0
          ]
        }
      ]
    },
    {
      "x": 6.359,
      "y": 27.919,
      "w": 8.88,
      "clr": 0,
      "sw": 0.36196875,
      "A": "left",
      "R": [
        {
          "T": "18",
          "S": -1,
          "TS": [
            0,
            11.04,
            0,
            0
          ]
        }
      ]
    },
    {
      "x": 8.256,
      "y": 27.919,
      "w": 105.018,
      "clr": 0,
      "sw": 0.36196875,
      "A": "left",
      "R": [
        {
          "T": "Fishback Studio of the Dance",
          "S": -1,
          "TS": [
            0,
            11.04,
            0,
            0
          ]
        }
      ]
    },
    {
      "x": 17.956,
      "y": 27.919,
      "w": 46.021,
      "clr": 0,
      "sw": 0.36196875,
      "A": "left",
      "R": [
        {
          "T": "GET HAPPY",
          "S": -1,
          "TS": [
            0,
            11.04,
            0,
            0
          ]
        }
      ]
    },
    {
      "x": 23.672,
      "y": 27.919,
      "w": 96.954,
      "clr": 0,
      "sw": 0.36196875,
      "A": "left",
      "R": [
        {
          "T": "ALLANA SALZBRENNER  ",
          "S": -1,
          "TS": [
            0,
            11.04,
            0,
            0
          ]
        }
      ]
    },
    {
      "x": 3.072,
      "y": 29.862,
      "w": 37.981,
      "clr": 0,
      "sw": 0.36196875,
      "A": "left",
      "R": [
        {
          "T": "Placement",
          "S": -1,
          "TS": [
            0,
            11.04,
            0,
            0
          ]
        }
      ]
    },
    {
      "x": 5.729,
      "y": 29.862,
      "w": 29.04,
      "clr": 0,
      "sw": 0.36196875,
      "A": "left",
      "R": [
        {
          "T": "Entry ID",
          "S": -1,
          "TS": [
            0,
            11.04,
            0,
            0
          ]
        }
      ]
    },
    {
      "x": 10.086,
      "y": 29.862,
      "w": 46.471,
      "clr": 0,
      "sw": 0.36196875,
      "A": "left",
      "R": [
        {
          "T": "Studio Name",
          "S": -1,
          "TS": [
            0,
            11.04,
            0,
            0
          ]
        }
      ]
    },
    {
      "x": 17.993,
      "y": 29.862,
      "w": 45.129,
      "clr": 0,
      "sw": 0.36196875,
      "A": "left",
      "R": [
        {
          "T": "Routine Title",
          "S": -1,
          "TS": [
            0,
            11.04,
            0,
            0
          ]
        }
      ]
    },
    {
      "x": 3.087,
      "y": 30.769,
      "w": 37.965,
      "clr": 0,
      "sw": 0.36196875,
      "A": "left",
      "R": [
        {
          "T": "DIAMOND",
          "S": -1,
          "TS": [
            0,
            11.04,
            0,
            0
          ]
        }
      ]
    },
    {
      "x": 6.359,
      "y": 30.822,
      "w": 8.88,
      "clr": 0,
      "sw": 0.36196875,
      "A": "left",
      "R": [
        {
          "T": "22",
          "S": -1,
          "TS": [
            0,
            11.04,
            0,
            0
          ]
        }
      ]
    },
    {
      "x": 7.671,
      "y": 30.822,
      "w": 123.776,
      "clr": 0,
      "sw": 0.36196875,
      "A": "left",
      "R": [
        {
          "T": "Aspire Dance Company of El Paso",
          "S": -1,
          "TS": [
            0,
            11.04,
            0,
            0
          ]
        }
      ]
    },
    {
      "x": 18.631,
      "y": 30.822,
      "w": 24.57,
      "clr": 0,
      "sw": 0.36196875,
      "A": "left",
      "R": [
        {
          "T": "DRIVE",
          "S": -1,
          "TS": [
            0,
            11.04,
            0,
            0
          ]
        }
      ]
    },
    {
      "x": 3.072,
      "y": 32.764,
      "w": 37.981,
      "clr": 0,
      "sw": 0.36196875,
      "A": "left",
      "R": [
        {
          "T": "Placement",
          "S": -1,
          "TS": [
            0,
            11.04,
            0,
            0
          ]
        }
      ]
    },
    {
      "x": 5.729,
      "y": 32.764,
      "w": 29.04,
      "clr": 0,
      "sw": 0.36196875,
      "A": "left",
      "R": [
        {
          "T": "Entry ID",
          "S": -1,
          "TS": [
            0,
            11.04,
            0,
            0
          ]
        }
      ]
    },
    {
      "x": 10.086,
      "y": 32.764,
      "w": 46.471,
      "clr": 0,
      "sw": 0.36196875,
      "A": "left",
      "R": [
        {
          "T": "Studio Name",
          "S": -1,
          "TS": [
            0,
            11.04,
            0,
            0
          ]
        }
      ]
    },
    {
      "x": 17.993,
      "y": 32.764,
      "w": 45.129,
      "clr": 0,
      "sw": 0.36196875,
      "A": "left",
      "R": [
        {
          "T": "Routine Title",
          "S": -1,
          "TS": [
            0,
            11.04,
            0,
            0
          ]
        }
      ]
    },
    {
      "x": 3.087,
      "y": 33.672,
      "w": 37.965,
      "clr": 0,
      "sw": 0.36196875,
      "A": "left",
      "R": [
        {
          "T": "DIAMOND",
          "S": -1,
          "TS": [
            0,
            11.04,
            0,
            0
          ]
        }
      ]
    },
    {
      "x": 6.216,
      "y": 33.724,
      "w": 13.32,
      "clr": 0,
      "sw": 0.36196875,
      "A": "left",
      "R": [
        {
          "T": "110",
          "S": -1,
          "TS": [
            0,
            11.04,
            0,
            0
          ]
        }
      ]
    },
    {
      "x": 8.256,
      "y": 33.724,
      "w": 105.018,
      "clr": 0,
      "sw": 0.36196875,
      "A": "left",
      "R": [
        {
          "T": "Fishback Studio of the Dance",
          "S": -1,
          "TS": [
            0,
            11.04,
            0,
            0
          ]
        }
      ]
    },
    {
      "x": 17.783,
      "y": 33.724,
      "w": 51.376,
      "clr": 0,
      "sw": 0.36196875,
      "A": "left",
      "R": [
        {
          "T": "WAKE ME UP",
          "S": -1,
          "TS": [
            0,
            11.04,
            0,
            0
          ]
        }
      ]
    },
    {
      "x": 3.072,
      "y": 35.669,
      "w": 37.981,
      "clr": 0,
      "sw": 0.36196875,
      "A": "left",
      "R": [
        {
          "T": "Placement",
          "S": -1,
          "TS": [
            0,
            11.04,
            0,
            0
          ]
        }
      ]
    },
    {
      "x": 5.729,
      "y": 35.669,
      "w": 29.04,
      "clr": 0,
      "sw": 0.36196875,
      "A": "left",
      "R": [
        {
          "T": "Entry ID",
          "S": -1,
          "TS": [
            0,
            11.04,
            0,
            0
          ]
        }
      ]
    },
    {
      "x": 10.086,
      "y": 35.669,
      "w": 46.471,
      "clr": 0,
      "sw": 0.36196875,
      "A": "left",
      "R": [
        {
          "T": "Studio Name",
          "S": -1,
          "TS": [
            0,
            11.04,
            0,
            0
          ]
        }
      ]
    },
    {
      "x": 17.993,
      "y": 35.669,
      "w": 45.129,
      "clr": 0,
      "sw": 0.36196875,
      "A": "left",
      "R": [
        {
          "T": "Routine Title",
          "S": -1,
          "TS": [
            0,
            11.04,
            0,
            0
          ]
        }
      ]
    },
    {
      "x": 3.087,
      "y": 36.576,
      "w": 37.965,
      "clr": 0,
      "sw": 0.36196875,
      "A": "left",
      "R": [
        {
          "T": "DIAMOND",
          "S": -1,
          "TS": [
            0,
            11.04,
            0,
            0
          ]
        }
      ]
    },
    {
      "x": 6.216,
      "y": 36.629,
      "w": 13.32,
      "clr": 0,
      "sw": 0.36196875,
      "A": "left",
      "R": [
        {
          "T": "114",
          "S": -1,
          "TS": [
            0,
            11.04,
            0,
            0
          ]
        }
      ]
    },
    {
      "x": 7.671,
      "y": 36.629,
      "w": 123.776,
      "clr": 0,
      "sw": 0.36196875,
      "A": "left",
      "R": [
        {
          "T": "Aspire Dance Company of El Paso",
          "S": -1,
          "TS": [
            0,
            11.04,
            0,
            0
          ]
        }
      ]
    },
    {
      "x": 17.948,
      "y": 36.629,
      "w": 46.463,
      "clr": 0,
      "sw": 0.36196875,
      "A": "left",
      "R": [
        {
          "T": "GET READY",
          "S": -1,
          "TS": [
            0,
            11.04,
            0,
            0
          ]
        }
      ]
    },
    {
      "x": 3.072,
      "y": 38.571,
      "w": 37.981,
      "clr": 0,
      "sw": 0.36196875,
      "A": "left",
      "R": [
        {
          "T": "Placement",
          "S": -1,
          "TS": [
            0,
            11.04,
            0,
            0
          ]
        }
      ]
    },
    {
      "x": 5.729,
      "y": 38.571,
      "w": 29.04,
      "clr": 0,
      "sw": 0.36196875,
      "A": "left",
      "R": [
        {
          "T": "Entry ID",
          "S": -1,
          "TS": [
            0,
            11.04,
            0,
            0
          ]
        }
      ]
    },
    {
      "x": 10.086,
      "y": 38.571,
      "w": 46.471,
      "clr": 0,
      "sw": 0.36196875,
      "A": "left",
      "R": [
        {
          "T": "Studio Name",
          "S": -1,
          "TS": [
            0,
            11.04,
            0,
            0
          ]
        }
      ]
    },
    {
      "x": 17.993,
      "y": 38.571,
      "w": 45.129,
      "clr": 0,
      "sw": 0.36196875,
      "A": "left",
      "R": [
        {
          "T": "Routine Title",
          "S": -1,
          "TS": [
            0,
            11.04,
            0,
            0
          ]
        }
      ]
    },
    {
      "x": 25.209,
      "y": 38.571,
      "w": 47.806,
      "clr": 0,
      "sw": 0.36196875,
      "A": "left",
      "R": [
        {
          "T": "Soloist Name",
          "S": -1,
          "TS": [
            0,
            11.04,
            0,
            0
          ]
        }
      ]
    },
    {
      "x": 3.087,
      "y": 39.479,
      "w": 37.965,
      "clr": 0,
      "sw": 0.36196875,
      "A": "left",
      "R": [
        {
          "T": "DIAMOND",
          "S": -1,
          "TS": [
            0,
            11.04,
            0,
            0
          ]
        }
      ]
    },
    {
      "x": 6.359,
      "y": 39.531,
      "w": 8.88,
      "clr": 0,
      "sw": 0.36196875,
      "A": "left",
      "R": [
        {
          "T": "62",
          "S": -1,
          "TS": [
            0,
            11.04,
            0,
            0
          ]
        }
      ]
    },
    {
      "x": 9.209,
      "y": 39.531,
      "w": 75.045,
      "clr": 0,
      "sw": 0.36196875,
      "A": "left",
      "R": [
        {
          "T": "Music Moves Me NM",
          "S": -1,
          "TS": [
            0,
            11.04,
            0,
            0
          ]
        }
      ]
    },
    {
      "x": 18.353,
      "y": 39.531,
      "w": 33.503,
      "clr": 0,
      "sw": 0.36196875,
      "A": "left",
      "R": [
        {
          "T": "RESCUE",
          "S": -1,
          "TS": [
            0,
            11.04,
            0,
            0
          ]
        }
      ]
    },
    {
      "x": 24.782,
      "y": 39.531,
      "w": 61.659,
      "clr": 0,
      "sw": 0.36196875,
      "A": "left",
      "R": [
        {
          "T": "MAXA FLORES  ",
          "S": -1,
          "TS": [
            0,
            11.04,
            0,
            0
          ]
        }
      ]
    },
    {
      "x": 3.072,
      "y": 41.474,
      "w": 37.981,
      "clr": 0,
      "sw": 0.36196875,
      "A": "left",
      "R": [
        {
          "T": "Placement",
          "S": -1,
          "TS": [
            0,
            11.04,
            0,
            0
          ]
        }
      ]
    },
    {
      "x": 5.729,
      "y": 41.474,
      "w": 29.04,
      "clr": 0,
      "sw": 0.36196875,
      "A": "left",
      "R": [
        {
          "T": "Entry ID",
          "S": -1,
          "TS": [
            0,
            11.04,
            0,
            0
          ]
        }
      ]
    },
    {
      "x": 10.086,
      "y": 41.474,
      "w": 46.471,
      "clr": 0,
      "sw": 0.36196875,
      "A": "left",
      "R": [
        {
          "T": "Studio Name",
          "S": -1,
          "TS": [
            0,
            11.04,
            0,
            0
          ]
        }
      ]
    },
    {
      "x": 17.993,
      "y": 41.474,
      "w": 45.129,
      "clr": 0,
      "sw": 0.36196875,
      "A": "left",
      "R": [
        {
          "T": "Routine Title",
          "S": -1,
          "TS": [
            0,
            11.04,
            0,
            0
          ]
        }
      ]
    },
    {
      "x": 3.087,
      "y": 42.381,
      "w": 37.965,
      "clr": 0,
      "sw": 0.36196875,
      "A": "left",
      "R": [
        {
          "T": "DIAMOND",
          "S": -1,
          "TS": [
            0,
            11.04,
            0,
            0
          ]
        }
      ]
    },
    {
      "x": 6.359,
      "y": 42.434,
      "w": 8.88,
      "clr": 0,
      "sw": 0.36196875,
      "A": "left",
      "R": [
        {
          "T": "66",
          "S": -1,
          "TS": [
            0,
            11.04,
            0,
            0
          ]
        }
      ]
    },
    {
      "x": 8.384,
      "y": 42.434,
      "w": 100.99,
      "clr": 0,
      "sw": 0.36196875,
      "A": "left",
      "R": [
        {
          "T": "Dancing Stars Dance Studio",
          "S": -1,
          "TS": [
            0,
            11.04,
            0,
            0
          ]
        }
      ]
    },
    {
      "x": 17.288,
      "y": 42.434,
      "w": 67.464,
      "clr": 0,
      "sw": 0.36196875,
      "A": "left",
      "R": [
        {
          "T": "BREAKIN DISHES",
          "S": -1,
          "TS": [
            0,
            11.04,
            0,
            0
          ]
        }
      ]
    },
    {
      "x": 3.072,
      "y": 44.376,
      "w": 37.981,
      "clr": 0,
      "sw": 0.36196875,
      "A": "left",
      "R": [
        {
          "T": "Placement",
          "S": -1,
          "TS": [
            0,
            11.04,
            0,
            0
          ]
        }
      ]
    },
    {
      "x": 5.729,
      "y": 44.376,
      "w": 29.04,
      "clr": 0,
      "sw": 0.36196875,
      "A": "left",
      "R": [
        {
          "T": "Entry ID",
          "S": -1,
          "TS": [
            0,
            11.04,
            0,
            0
          ]
        }
      ]
    },
    {
      "x": 10.086,
      "y": 44.376,
      "w": 46.471,
      "clr": 0,
      "sw": 0.36196875,
      "A": "left",
      "R": [
        {
          "T": "Studio Name",
          "S": -1,
          "TS": [
            0,
            11.04,
            0,
            0
          ]
        }
      ]
    },
    {
      "x": 17.993,
      "y": 44.376,
      "w": 45.129,
      "clr": 0,
      "sw": 0.36196875,
      "A": "left",
      "R": [
        {
          "T": "Routine Title",
          "S": -1,
          "TS": [
            0,
            11.04,
            0,
            0
          ]
        }
      ]
    },
    {
      "x": 3.087,
      "y": 43.483,
      "w": 210.67,
      "clr": 0,
      "sw": 0.36196875,
      "A": "left",
      "R": [
        {
          "T": "Novice Gems ~ Senior ~ Duo/Trio",
          "S": -1,
          "TS": [
            0,
            17.04,
            0,
            0
          ]
        }
      ]
    },
    {
      "x": 12.406,
      "y": 8.664,
      "w": 130.425,
      "clr": 0,
      "sw": 0.36196875,
      "A": "left",
      "R": [
        {
          "T": "Albuquerque 2026",
          "S": -1,
          "TS": [
            0,
            18.96,
            0,
            0
          ]
        }
      ]
    },
    {
      "x": 13.096,
      "y": 9.886,
      "w": 108.193,
      "clr": 0,
      "sw": 0.36196875,
      "A": "left",
      "R": [
        {
          "T": "Overall Results",
          "S": -1,
          "TS": [
            0,
            18.96,
            0,
            0
          ]
        }
      ]
    },
    {
      "x": 3.087,
      "y": 11.004,
      "w": 180.26,
      "clr": 0,
      "sw": 0.36196875,
      "A": "left",
      "R": [
        {
          "T": "Novice Gems ~ Petite ~ Solo",
          "S": -1,
          "TS": [
            0,
            17.04,
            0,
            0
          ]
        }
      ]
    },
    {
      "x": 3.087,
      "y": 16.631,
      "w": 205.995,
      "clr": 0,
      "sw": 0.36196875,
      "A": "left",
      "R": [
        {
          "T": "Novice Gems ~ Petite ~ Duo/Trio",
          "S": -1,
          "TS": [
            0,
            17.04,
            0,
            0
          ]
        }
      ]
    },
    {
      "x": 3.087,
      "y": 31.872,
      "w": 232.516,
      "clr": 0,
      "sw": 0.36196875,
      "A": "left",
      "R": [
        {
          "T": "Novice Gems ~ Junior ~ Small Group",
          "S": -1,
          "TS": [
            0,
            17.04,
            0,
            0
          ]
        }
      ]
    },
    {
      "x": 3.087,
      "y": 34.774,
      "w": 233.317,
      "clr": 0,
      "sw": 0.36196875,
      "A": "left",
      "R": [
        {
          "T": "Novice Gems ~ Junior ~ Large Group",
          "S": -1,
          "TS": [
            0,
            17.04,
            0,
            0
          ]
        }
      ]
    },
    {
      "x": 3.087,
      "y": 37.679,
      "w": 176.356,
      "clr": 0,
      "sw": 0.36196875,
      "A": "left",
      "R": [
        {
          "T": "Novice Gems ~ Teen ~ Solo",
          "S": -1,
          "TS": [
            0,
            17.04,
            0,
            0
          ]
        }
      ]
    },
    {
      "x": 3.087,
      "y": 40.581,
      "w": 202.092,
      "clr": 0,
      "sw": 0.36196875,
      "A": "left",
      "R": [
        {
          "T": "Novice Gems ~ Teen ~ Duo/Trio",
          "S": -1,
          "TS": [
            0,
            17.04,
            0,
            0
          ]
        }
      ]
    },
    {
      "x": 3.087,
      "y": 19.533,
      "w": 230.186,
      "clr": 0,
      "sw": 0.36196875,
      "A": "left",
      "R": [
        {
          "T": "Novice Gems ~ Petite ~ Small Group",
          "S": -1,
          "TS": [
            0,
            17.04,
            0,
            0
          ]
        }
      ]
    },
    {
      "x": 3.087,
      "y": 23.343,
      "w": 182.59,
      "clr": 0,
      "sw": 0.36196875,
      "A": "left",
      "R": [
        {
          "T": "Novice Gems ~ Junior ~ Solo",
          "S": -1,
          "TS": [
            0,
            17.04,
            0,
            0
          ]
        }
      ]
    },
    {
      "x": 3.087,
      "y": 28.969,
      "w": 208.326,
      "clr": 0,
      "sw": 0.36196875,
      "A": "left",
      "R": [
        {
          "T": "Novice Gems ~ Junior ~ Duo/Trio",
          "S": -1,
          "TS": [
            0,
            17.04,
            0,
            0
          ]
        }
      ]
    }
  ],
  "Fields": [],
  "Boxsets": []
}